cricket_rankings/__init__.py
cricket_rankings/rankings.py
cricket_rankings-1.0.3.dist-info/LICENSE
cricket_rankings-1.0.3.dist-info/METADATA
cricket_rankings-1.0.3.dist-info/WHEEL
cricket_rankings-1.0.3.dist-info/top_level.txt
cricket_rankings-1.0.3.dist-info/RECORD
