Metadata-Version: 2.1
Name: cricket-rankings
Version: 1.0.3
Summary: Cricket rankings of teams and players across all the formats for both men and women
Home-page: http://github.com/umangahuja1/cricket_rankings
Author: Umang Ahuja
Author-email: umangahuja1@gmail.com
License: MIT
Keywords: package cricket cricket-rankings cricket_rankings
Platform: UNKNOWN
Classifier: Programming Language :: Python :: 3
Classifier: License :: OSI Approved :: MIT License
Classifier: Operating System :: OS Independent
Requires-Dist: beautifulsoup4 (==4.6.0)
Requires-Dist: bs4 (==0.0.1)
Requires-Dist: certifi (==2018.4.16)
Requires-Dist: chardet (==3.0.4)
Requires-Dist: idna (==2.7)
Requires-Dist: lxml (==4.2.2)
Requires-Dist: requests (>=2.20.0)
Requires-Dist: urllib3 (==1.23)
